[{"year": "1972", "title": "the godfather", "ranking": 2, "ranking_women": 10, "ranking_men": 2, "gender_score": 0.01603206412825653}, {"year": "2008", "title": "the dark knight", "ranking": 4, "ranking_women": 3, "ranking_men": 3, "gender_score": 0.0}, {"year": "2003", "title": "the lord of the rings: the return of the king", "ranking": 8, "ranking_women": 2, "ranking_men": 4, "gender_score": -0.004008016032064132}, {"year": "1993", "title": "schindler\u2019s list", "ranking": 6, "ranking_women": 6, "ranking_men": 11, "gender_score": -0.01002004008016033}, {"year": "1999", "title": "fight club", "ranking": 10, "ranking_women": 5, "ranking_men": 8, "gender_score": -0.006012024048096198}, {"year": "2001", "title": "the lord of the rings: the fellowship of the ring", "ranking": 11, "ranking_women": 7, "ranking_men": 10, "gender_score": -0.006012024048096198}, {"year": "1957", "title": "12 angry men", "ranking": 5, "ranking_women": 27, "ranking_men": 7, "gender_score": 0.04008016032064132}, {"year": "1974", "title": "the godfather: part ii", "ranking": 3, "ranking_women": 22, "ranking_men": 5, "gender_score": 0.034068136272545124}, {"year": "2010", "title": "inception", "ranking": 14, "ranking_women": 8, "ranking_men": 6, "gender_score": 0.004008016032064132}, {"year": "1994", "title": "forrest gump", "ranking": 12, "ranking_women": 9, "ranking_men": 13, "gender_score": -0.008016032064128265}, {"year": "2002", "title": "the lord of the rings: the two towers", "ranking": 15, "ranking_women": 11, "ranking_men": 14, "gender_score": -0.006012024048096198}, {"year": "1994", "title": "the lion king", "ranking": 47, "ranking_women": 4, "ranking_men": 29, "gender_score": -0.05010020040080165}, {"year": "1994", "title": "pulp fiction", "ranking": 7, "ranking_women": 15, "ranking_men": 9, "gender_score": 0.012024048096192397}, {"year": "2014", "title": "interstellar", "ranking": 30, "ranking_women": 25, "ranking_men": 15, "gender_score": 0.02004008016032066}, {"year": "1999", "title": "the green mile", "ranking": 32, "ranking_women": 12, "ranking_men": 28, "gender_score": -0.03206412825651295}, {"year": "1975", "title": "one flew over the cuckoo\u2019s nest", "ranking": 16, "ranking_women": 24, "ranking_men": 19, "gender_score": 0.01002004008016033}, {"year": "1966", "title": "the good, the bad and the ugly", "ranking": 9, "ranking_women": 115, "ranking_men": 12, "gender_score": 0.2064128256513026}, {"year": "2006", "title": "the prestige", "ranking": 48, "ranking_women": 26, "ranking_men": 16, "gender_score": 0.02004008016032066}, {"year": "1998", "title": "american history x", "ranking": 31, "ranking_women": 17, "ranking_men": 27, "gender_score": -0.02004008016032066}, {"year": "2012", "title": "the dark knight rises", "ranking": 65, "ranking_women": 23, "ranking_men": 22, "gender_score": 0.002004008016032066}, {"year": "1997", "title": "life is beautiful", "ranking": 25, "ranking_women": 16, "ranking_men": 41, "gender_score": -0.05010020040080154}, {"year": "1980", "title": "star wars: episode v \u2013 the empire strikes back", "ranking": 13, "ranking_women": 41, "ranking_men": 17, "gender_score": 0.048096192384769476}, {"year": "1994", "title": "leon: the professional", "ranking": 27, "ranking_women": 21, "ranking_men": 37, "gender_score": -0.03206412825651295}, {"year": "2002", "title": "city of god", "ranking": 21, "ranking_women": 64, "ranking_men": 20, "gender_score": 0.0881763527054108}, {"year": "1995", "title": "se7en", "ranking": 22, "ranking_women": 28, "ranking_men": 23, "gender_score": 0.01002004008016022}, {"year": "2001", "title": "spirited away", "ranking": 28, "ranking_women": 13, "ranking_men": 56, "gender_score": -0.08617234468937873}, {"year": "1991", "title": "the silence of the lambs", "ranking": 23, "ranking_women": 20, "ranking_men": 33, "gender_score": -0.02605210420841675}, {"year": "2006", "title": "the departed", "ranking": 40, "ranking_women": 35, "ranking_men": 26, "gender_score": 0.018036072144288484}, {"year": "1990", "title": "goodfellas", "ranking": 17, "ranking_women": 71, "ranking_men": 18, "gender_score": 0.1062124248496994}, {"year": "2011", "title": "the intouchables", "ranking": 37, "ranking_women": 19, "ranking_men": 52, "gender_score": -0.06613226452905807}, {"year": "2014", "title": "whiplash", "ranking": 45, "ranking_women": 54, "ranking_men": 30, "gender_score": 0.04809619238476959}, {"year": "2000", "title": "gladiator", "ranking": 46, "ranking_women": 44, "ranking_men": 24, "gender_score": 0.04008016032064121}, {"year": "2012", "title": "django unchained", "ranking": 60, "ranking_women": 29, "ranking_men": 31, "gender_score": -0.004008016032064021}, {"year": "2002", "title": "the pianist", "ranking": 39, "ranking_women": 31, "ranking_men": 53, "gender_score": -0.044088176352705455}, {"year": "1946", "title": "it\u2019s a wonderful life", "ranking": 24, "ranking_women": 56, "ranking_men": 51, "gender_score": 0.01002004008016033}, {"year": "1960", "title": "psycho", "ranking": 34, "ranking_women": 55, "ranking_men": 40, "gender_score": 0.030060120240480992}, {"year": "1977", "title": "star wars: episode iv \u2013 a new hope", "ranking": 20, "ranking_women": 48, "ranking_men": 32, "gender_score": 0.03206412825651306}, {"year": "2009", "title": "inglourious basterds", "ranking": 97, "ranking_women": 32, "ranking_men": 43, "gender_score": -0.022044088176352727}, {"year": "1998", "title": "saving private ryan", "ranking": 29, "ranking_women": 70, "ranking_men": 25, "gender_score": 0.09018036072144286}, {"year": "1995", "title": "the usual suspects", "ranking": 26, "ranking_women": 58, "ranking_men": 36, "gender_score": 0.044088176352705455}, {"year": "1999", "title": "the matrix", "ranking": 18, "ranking_women": 62, "ranking_men": 21, "gender_score": 0.0821643286573146}, {"year": "2000", "title": "memento", "ranking": 49, "ranking_women": 57, "ranking_men": 34, "gender_score": 0.04609218436873752}, {"year": "1942", "title": "casablanca", "ranking": 36, "ranking_women": 73, "ranking_men": 42, "gender_score": 0.06212424849699405}, {"year": "1999", "title": "american beauty", "ranking": 63, "ranking_women": 51, "ranking_men": 35, "gender_score": 0.03206412825651306}, {"year": "1985", "title": "back to the future", "ranking": 44, "ranking_women": 49, "ranking_men": 46, "gender_score": 0.006012024048096198}, {"year": "2001", "title": "a beautiful mind", "ranking": 144, "ranking_women": 34, "ranking_men": 68, "gender_score": -0.06813627254509025}, {"year": "1954", "title": "rear window", "ranking": 43, "ranking_women": 80, "ranking_men": 60, "gender_score": 0.04008016032064132}, {"year": "2000", "title": "requiem for a dream", "ranking": 80, "ranking_women": 50, "ranking_men": 49, "gender_score": 0.002004008016032066}, {"year": "2011", "title": "harry potter and the deathly hallows: part 2", "ranking": 218, "ranking_women": 14, "ranking_men": 126, "gender_score": -0.22444889779559107}, {"year": "2006", "title": "the lives of others", "ranking": 58, "ranking_women": 86, "ranking_men": 78, "gender_score": 0.01603206412825653}, {"year": "2010", "title": "shutter island", "ranking": 177, "ranking_women": 39, "ranking_men": 59, "gender_score": -0.04008016032064132}, {"year": "2008", "title": "wall-e", "ranking": 62, "ranking_women": 42, "ranking_men": 62, "gender_score": -0.04008016032064132}, {"year": "2004", "title": "eternal sunshine of the spotless mind", "ranking": 87, "ranking_women": 38, "ranking_men": 66, "gender_score": -0.05611222444889785}, {"year": "1980", "title": "the shining", "ranking": 61, "ranking_women": 61, "ranking_men": 47, "gender_score": 0.028056112224448926}, {"year": "1997", "title": "good will hunting", "ranking": 102, "ranking_women": 60, "ranking_men": 48, "gender_score": 0.024048096192384794}, {"year": "1971", "title": "a clockwork orange", "ranking": 84, "ranking_women": 79, "ranking_men": 50, "gender_score": 0.05811623246492981}, {"year": "2001", "title": "amelie", "ranking": 82, "ranking_women": 30, "ranking_men": 90, "gender_score": -0.12024048096192397}, {"year": "1954", "title": "seven samurai", "ranking": 19, "ranking_women": 336, "ranking_men": 39, "gender_score": 0.5951903807615231}, {"year": "1983", "title": "star wars: episode vi \u2013 return of the jedi", "ranking": 76, "ranking_women": 87, "ranking_men": 63, "gender_score": 0.048096192384769476}, {"year": "1992", "title": "reservoir dogs", "ranking": 77, "ranking_women": 94, "ranking_men": 64, "gender_score": 0.06012024048096187}, {"year": "2017", "title": "coco", "ranking": 51, "ranking_women": 209, "ranking_men": 166, "gender_score": 0.08617234468937873}, {"year": "1988", "title": "cinema paradiso", "ranking": 54, "ranking_women": 165, "ranking_men": 97, "gender_score": 0.13627254509018039}, {"year": "1979", "title": "apocalypse now", "ranking": 50, "ranking_women": 219, "ranking_men": 38, "gender_score": 0.36272545090180364}, {"year": "1940", "title": "the great dictator", "ranking": 53, "ranking_women": 262, "ranking_men": 101, "gender_score": 0.3226452905811623}, {"year": "1950", "title": "sunset boulevard", "ranking": 55, "ranking_women": 190, "ranking_men": 108, "gender_score": 0.1643286573146293}, {"year": "1931", "title": "city lights", "ranking": 35, "ranking_women": 294, "ranking_men": 92, "gender_score": 0.404809619238477}, {"year": "1997", "title": "princess mononoke", "ranking": 64, "ranking_women": 118, "ranking_men": 100, "gender_score": 0.03607214428857719}, {"year": "2015", "title": "room", "ranking": 143, "ranking_women": 82, "ranking_men": 139, "gender_score": -0.11422845691382766}, {"year": "2003", "title": "pirates of the caribbean: the curse of the black pearl >", "ranking": 250, "ranking_women": 36, "ranking_men": 113, "gender_score": -0.15430861723446898}, {"year": "2004", "title": "howl\u2019s moving castle", "ranking": 137, "ranking_women": 43, "ranking_men": 216, "gender_score": -0.3466933867735471}, {"year": "1962", "title": "to kill a mockingbird", "ranking": 89, "ranking_women": 102, "ranking_men": 135, "gender_score": -0.06613226452905818}, {"year": "2009", "title": "up", "ranking": 115, "ranking_women": 37, "ranking_men": 117, "gender_score": -0.16032064128256518}, {"year": "2014", "title": "gone girl", "ranking": 179, "ranking_women": 81, "ranking_men": 70, "gender_score": 0.022044088176352616}, {"year": "2010", "title": "toy story 3", "ranking": 98, "ranking_women": 66, "ranking_men": 82, "gender_score": -0.03206412825651306}, {"year": "1936", "title": "modern times", "ranking": 38, "ranking_women": 248, "ranking_men": 96, "gender_score": 0.3046092184368737}, {"year": "1988", "title": "grave of the fireflies", "ranking": 57, "ranking_women": 159, "ranking_men": 133, "gender_score": 0.05210420841683361}, {"year": "2006", "title": "pan\u2019s labyrinth", "ranking": 130, "ranking_women": 74, "ranking_men": 91, "gender_score": -0.03406813627254501}, {"year": "2016", "title": "hacksaw ridge", "ranking": 175, "ranking_women": 161, "ranking_men": 124, "gender_score": 0.07414829659318634}, {"year": "1968", "title": "2001: a space odyssey", "ranking": 91, "ranking_women": 195, "ranking_men": 54, "gender_score": 0.282565130260521}, {"year": "2007", "title": "into the wild", "ranking": 181, "ranking_women": 84, "ranking_men": 95, "gender_score": -0.022044088176352616}, {"year": "1958", "title": "vertigo", "ranking": 72, "ranking_women": 154, "ranking_men": 87, "gender_score": 0.13426853707414832}, {"year": "2015", "title": "inside out", "ranking": 140, "ranking_women": 78, "ranking_men": 107, "gender_score": -0.05811623246492981}, {"year": "2005", "title": "batman begins", "ranking": 116, "ranking_women": 106, "ranking_men": 58, "gender_score": 0.09619238476953906}, {"year": "1975", "title": "monty python and the holy grail", "ranking": 103, "ranking_women": 123, "ranking_men": 104, "gender_score": 0.038076152304609256}, {"year": "2009", "title": "3 idiots", "ranking": 93, "ranking_women": 203, "ranking_men": 93, "gender_score": 0.22044088176352705}, {"year": "2003", "title": "oldeuboi", "ranking": 67, "ranking_women": 171, "ranking_men": 73, "gender_score": 0.19639278557114226}, {"year": "1964", "title": "dr. strangelove or: how i learned to stop worrying and love the bomb", "ranking": 56, "ranking_women": 236, "ranking_men": 57, "gender_score": 0.3587174348697395}, {"year": "1991", "title": "terminator 2", "ranking": 42, "ranking_women": 178, "ranking_men": 44, "gender_score": 0.26853707414829664}, {"year": "1959", "title": "north by northwest", "ranking": 74, "ranking_women": 205, "ranking_men": 99, "gender_score": 0.2124248496993988}, {"year": "1968", "title": "once upon a time in the west", "ranking": 33, "ranking_women": 447, "ranking_men": 55, "gender_score": 0.7855711422845691}, {"year": "1981", "title": "raiders of the lost ark", "ranking": 41, "ranking_women": 131, "ranking_men": 65, "gender_score": 0.13226452905811625}, {"year": "1995", "title": "toy story", "ranking": 94, "ranking_women": 85, "ranking_men": 80, "gender_score": 0.01002004008016022}, {"year": "1952", "title": "singin\u2019 in the rain", "ranking": 90, "ranking_women": 110, "ranking_men": 170, "gender_score": -0.12024048096192386}, {"year": "2016", "title": "la la land", "ranking": 207, "ranking_women": 122, "ranking_men": 86, "gender_score": 0.07214428857715427}, {"year": "1979", "title": "alien", "ranking": 52, "ranking_women": 151, "ranking_men": 67, "gender_score": 0.16833667334669344}, {"year": "1941", "title": "citizen kane", "ranking": 71, "ranking_women": 188, "ranking_men": 74, "gender_score": 0.22845691382765532}, {"year": "2002", "title": "catch me if you can", "ranking": 219, "ranking_women": 97, "ranking_men": 81, "gender_score": 0.03206412825651306}, {"year": "1983", "title": "scarface", "ranking": 105, "ranking_women": 181, "ranking_men": 69, "gender_score": 0.22444889779559118}, {"year": "1976", "title": "taxi driver", "ranking": 88, "ranking_women": 164, "ranking_men": 71, "gender_score": 0.18637274549098193}, {"year": "2014", "title": "the grand budapest hotel", "ranking": 194, "ranking_women": 65, "ranking_men": 128, "gender_score": -0.12625250501001994}, {"year": "1987", "title": "full metal jacket", "ranking": 92, "ranking_women": 177, "ranking_men": 83, "gender_score": 0.1883767535070141}, {"year": "2010", "title": "how to train your dragon", "ranking": 176, "ranking_women": 47, "ranking_men": 165, "gender_score": -0.23647294589178358}, {"year": "1984", "title": "amadeus", "ranking": 83, "ranking_women": 128, "ranking_men": 121, "gender_score": 0.014028056112224352}, {"year": "2007", "title": "there will be blood", "ranking": 165, "ranking_women": 212, "ranking_men": 72, "gender_score": 0.2805611222444889}, {"year": "2012", "title": "the avengers >", "ranking": 250, "ranking_women": 52, "ranking_men": 144, "gender_score": -0.18436873747494986}, {"year": "1984", "title": "once upon a time in america", "ranking": 69, "ranking_women": 337, "ranking_men": 88, "gender_score": 0.4989979959919839}, {"year": "2013", "title": "the wolf of wall street", "ranking": 150, "ranking_women": 158, "ranking_men": 45, "gender_score": 0.22645290581162325}, {"year": "2005", "title": "v for vendetta", "ranking": 151, "ranking_women": 76, "ranking_men": 112, "gender_score": -0.07214428857715427}, {"year": "1939", "title": "gone with the wind", "ranking": 157, "ranking_women": 46, "ranking_men": 279, "gender_score": -0.46693386773547096}, {"year": "2003", "title": "kill bill: vol. 1", "ranking": 174, "ranking_women": 89, "ranking_men": 114, "gender_score": -0.05010020040080165}, {"year": "1995", "title": "braveheart", "ranking": 75, "ranking_women": 141, "ranking_men": 61, "gender_score": 0.16032064128256518}, {"year": "2003", "title": "finding nemo", "ranking": 166, "ranking_women": 53, "ranking_men": 151, "gender_score": -0.19639278557114237}, {"year": "1999", "title": "the sixth sense", "ranking": 160, "ranking_women": 75, "ranking_men": 116, "gender_score": -0.0821643286573146}, {"year": "2011", "title": "the help", "ranking": 241, "ranking_women": 33, "ranking_men": 245, "gender_score": -0.4248496993987977}, {"year": "2015", "title": "star wars: the force awakens >", "ranking": 250, "ranking_women": 92, "ranking_men": 154, "gender_score": -0.12424849699398799}, {"year": "2015", "title": "mad max: fury road", "ranking": 204, "ranking_women": 135, "ranking_men": 79, "gender_score": 0.1122244488977957}, {"year": "2000", "title": "snatch", "ranking": 100, "ranking_women": 144, "ranking_men": 76, "gender_score": 0.13627254509018027}, {"year": "2016", "title": "dangal", "ranking": 73, "ranking_women": 649, "ranking_men": 195, "gender_score": 0.9098196392785571}, {"year": "2016", "title": "zootopia >", "ranking": 250, "ranking_women": 95, "ranking_men": 187, "gender_score": -0.18436873747494986}, {"year": "2001", "title": "donnie darko", "ranking": 226, "ranking_women": 91, "ranking_men": 122, "gender_score": -0.06212424849699405}, {"year": "2008", "title": "gran torino", "ranking": 158, "ranking_women": 121, "ranking_men": 120, "gender_score": 0.002004008016032066}, {"year": "1989", "title": "indiana jones and the last crusade", "ranking": 112, "ranking_women": 156, "ranking_men": 84, "gender_score": 0.14428857715430854}, {"year": "2012", "title": "jagten", "ranking": 101, "ranking_women": 183, "ranking_men": 141, "gender_score": 0.08416833667334656}, {"year": "1988", "title": "my neighbor totoro", "ranking": 132, "ranking_women": 112, "ranking_men": 183, "gender_score": -0.14228456913827647}, {"year": "1996", "title": "trainspotting", "ranking": 156, "ranking_women": 107, "ranking_men": 127, "gender_score": -0.04008016032064132}, {"year": "2013", "title": "12 years a slave", "ranking": 201, "ranking_women": 100, "ranking_men": 131, "gender_score": -0.06212424849699405}, {"year": "1959", "title": "some like it hot", "ranking": 118, "ranking_women": 124, "ranking_men": 186, "gender_score": -0.12424849699398799}, {"year": "1973", "title": "the sting", "ranking": 95, "ranking_women": 284, "ranking_men": 143, "gender_score": 0.282565130260521}, {"year": "2013", "title": "prisoners", "ranking": 215, "ranking_women": 148, "ranking_men": 98, "gender_score": 0.1002004008016032}, {"year": "2017", "title": "logan", "ranking": 202, "ranking_women": 193, "ranking_men": 103, "gender_score": 0.18036072144288573}, {"year": "2016", "title": "your name", "ranking": 79, "ranking_women": 399, "ranking_men": 190, "gender_score": 0.4188376753507014}, {"year": "2007", "title": "taare zameen par", "ranking": 81, "ranking_women": 448, "ranking_men": 138, "gender_score": 0.62124248496994}, {"year": "2011", "title": "a separation", "ranking": 109, "ranking_women": 242, "ranking_men": 125, "gender_score": 0.2344689378757514}, {"year": "1997", "title": "titanic >", "ranking": 250, "ranking_women": 45, "ranking_men": 188, "gender_score": -0.28657314629258523}, {"year": "2011", "title": "warrior", "ranking": 154, "ranking_women": 213, "ranking_men": 134, "gender_score": 0.1583166332665331}, {"year": "2017", "title": "dunkirk", "ranking": 236, "ranking_women": 192, "ranking_men": 145, "gender_score": 0.094188376753507}, {"year": "2015", "title": "spotlight", "ranking": 205, "ranking_women": 155, "ranking_men": 152, "gender_score": 0.006012024048096198}, {"year": "1986", "title": "stand by me", "ranking": 192, "ranking_women": 125, "ranking_men": 184, "gender_score": -0.11823647294589179}, {"year": "2014", "title": "x-men: days of future past >", "ranking": 250, "ranking_women": 113, "ranking_men": 159, "gender_score": -0.09218436873747493}, {"year": "2004", "title": "kill bill: vol. 2 >", "ranking": 250, "ranking_women": 116, "ranking_men": 157, "gender_score": -0.0821643286573146}, {"year": "2014", "title": "the imitation game >", "ranking": 250, "ranking_women": 69, "ranking_men": 209, "gender_score": -0.2805611222444889}, {"year": "2010", "title": "the king\u2019s speech >", "ranking": 250, "ranking_women": 59, "ranking_men": 206, "gender_score": -0.2945891783567135}, {"year": "1986", "title": "aliens", "ranking": 68, "ranking_women": 217, "ranking_men": 85, "gender_score": 0.2645290581162325}, {"year": "2004", "title": "downfall", "ranking": 121, "ranking_women": 288, "ranking_men": 115, "gender_score": 0.3466933867735471}, {"year": "1998", "title": "lock, stock and two smoking barrels", "ranking": 142, "ranking_women": 199, "ranking_men": 130, "gender_score": 0.13827655310621245}, {"year": "1997", "title": "l.a. confidential", "ranking": 106, "ranking_women": 225, "ranking_men": 94, "gender_score": 0.26252505010020044}, {"year": "2016", "title": "arrival >", "ranking": 250, "ranking_women": 169, "ranking_men": 137, "gender_score": 0.064128256513026}, {"year": "1957", "title": "paths of glory", "ranking": 59, "ranking_women": 704, "ranking_men": 109, "gender_score": 1.1923847695390781}, {"year": "2017", "title": "blade runner 2049", "ranking": 147, "ranking_women": 368, "ranking_men": 102, "gender_score": 0.533066132264529}, {"year": "1991", "title": "beauty and the beast", "ranking": 247, "ranking_women": 40, "ranking_men": 379, "gender_score": -0.6793587174348698}, {"year": "2014", "title": "guardians of the galaxy >", "ranking": 250, "ranking_women": 111, "ranking_men": 147, "gender_score": -0.07214428857715438}, {"year": "1962", "title": "lawrence of arabia", "ranking": 85, "ranking_women": 396, "ranking_men": 105, "gender_score": 0.5831663326653307}, {"year": "1993", "title": "jurassic park", "ranking": 198, "ranking_women": 150, "ranking_men": 118, "gender_score": 0.064128256513026}, {"year": "1927", "title": "metropolis", "ranking": 108, "ranking_women": 331, "ranking_men": 182, "gender_score": 0.2985971943887775}, {"year": "2016", "title": "deadpool >", "ranking": 250, "ranking_women": 126, "ranking_men": 155, "gender_score": -0.05811623246492992}, {"year": "2012", "title": "the hobbit: an unexpected journey >", "ranking": 250, "ranking_women": 90, "ranking_men": 192, "gender_score": -0.20440881763527052}, {"year": "2001", "title": "monsters, inc.", "ranking": 224, "ranking_women": 77, "ranking_men": 196, "gender_score": -0.23847695390781565}, {"year": "1988", "title": "die hard", "ranking": 122, "ranking_women": 220, "ranking_men": 77, "gender_score": 0.2865731462925851}, {"year": "1989", "title": "dead poets society", "ranking": 238, "ranking_women": 103, "ranking_men": 239, "gender_score": -0.27254509018036077}, {"year": "2010", "title": "black swan >", "ranking": 250, "ranking_women": 98, "ranking_men": 161, "gender_score": -0.12625250501002006}, {"year": "2015", "title": "the martian >", "ranking": 250, "ranking_women": 134, "ranking_men": 160, "gender_score": -0.05210420841683372}, {"year": "1957", "title": "witness for the prosecution", "ranking": 66, "ranking_women": 476, "ranking_men": 229, "gender_score": 0.4949899799599198}, {"year": "2004", "title": "hotel rwanda", "ranking": 190, "ranking_women": 176, "ranking_men": 181, "gender_score": -0.01002004008016033}, {"year": "2009", "title": "star trek >", "ranking": 250, "ranking_women": 117, "ranking_men": 199, "gender_score": -0.1643286573146292}, {"year": "2013", "title": "the hobbit: the desolation of smaug >", "ranking": 250, "ranking_women": 109, "ranking_men": 205, "gender_score": -0.19238476953907813}, {"year": "2009", "title": "hachi: a dog\u2019s tale", "ranking": 212, "ranking_women": 127, "ranking_men": 288, "gender_score": -0.3226452905811623}, {"year": "2017", "title": "three billboards outside ebbing, missouri", "ranking": 111, "ranking_women": 351, "ranking_men": 204, "gender_score": 0.2945891783567134}, {"year": "1981", "title": "das boot", "ranking": 70, "ranking_women": 603, "ranking_men": 111, "gender_score": 0.9859719438877756}, {"year": "1995", "title": "heat", "ranking": 123, "ranking_women": 332, "ranking_men": 89, "gender_score": 0.4869739478957916}, {"year": "1978", "title": "the deer hunter", "ranking": 159, "ranking_women": 346, "ranking_men": 153, "gender_score": 0.3867735470941883}, {"year": "1980", "title": "the elephant man", "ranking": 148, "ranking_women": 261, "ranking_men": 177, "gender_score": 0.16833667334669333}, {"year": "1931", "title": "m", "ranking": 78, "ranking_women": 465, "ranking_men": 167, "gender_score": 0.5971943887775552}, {"year": "1950", "title": "all about eve", "ranking": 114, "ranking_women": 227, "ranking_men": 302, "gender_score": -0.15030060120240485}, {"year": "1921", "title": "the kid", "ranking": 99, "ranking_women": 459, "ranking_men": 249, "gender_score": 0.42084168336673344}, {"year": "1944", "title": "double indemnity", "ranking": 86, "ranking_women": 433, "ranking_men": 169, "gender_score": 0.5290581162324649}, {"year": "2013", "title": "her >", "ranking": 250, "ranking_women": 194, "ranking_men": 106, "gender_score": 0.1763527054108217}, {"year": "2009", "title": "mary and max", "ranking": 178, "ranking_women": 175, "ranking_men": 274, "gender_score": -0.19839679358717432}, {"year": "2017", "title": "thor: ragnarok >", "ranking": 250, "ranking_women": 200, "ranking_men": 260, "gender_score": -0.12024048096192375}, {"year": "2013", "title": "dallas buyers club >", "ranking": 250, "ranking_women": 146, "ranking_men": 175, "gender_score": -0.05811623246492992}, {"year": "1960", "title": "the apartment", "ranking": 107, "ranking_women": 322, "ranking_men": 189, "gender_score": 0.2665330661322646}, {"year": "2008", "title": "in bruges >", "ranking": 250, "ranking_women": 239, "ranking_men": 140, "gender_score": 0.19839679358717444}, {"year": "1998", "title": "the truman show", "ranking": 206, "ranking_women": 132, "ranking_men": 149, "gender_score": -0.034068136272545235}, {"year": "2010", "title": "incendies", "ranking": 131, "ranking_women": 300, "ranking_men": 253, "gender_score": 0.09418837675350711}, {"year": "1939", "title": "the wizard of oz", "ranking": 232, "ranking_women": 119, "ranking_men": 241, "gender_score": -0.24448897795591185}, {"year": "2008", "title": "slumdog millionaire >", "ranking": 250, "ranking_women": 99, "ranking_men": 191, "gender_score": -0.18436873747494986}, {"year": "2007", "title": "no country for old men", "ranking": 162, "ranking_women": 244, "ranking_men": 75, "gender_score": 0.33867735470941873}, {"year": "1999", "title": "the boondock saints >", "ranking": 250, "ranking_women": 254, "ranking_men": 250, "gender_score": 0.008016032064128265}, {"year": "2009", "title": "the secret in their eyes", "ranking": 135, "ranking_women": 265, "ranking_men": 198, "gender_score": 0.1342685370741482}, {"year": "2016", "title": "lion >", "ranking": 250, "ranking_women": 170, "ranking_men": 332, "gender_score": -0.3246492985971944}, {"year": "2017", "title": "baahubali 2: the conclusion >", "ranking": 250, "ranking_women": 1170, "ranking_men": 343, "gender_score": 1.6573146292585168}, {"year": "2015", "title": "the revenant >", "ranking": 250, "ranking_women": 214, "ranking_men": 129, "gender_score": 0.1703406813627254}, {"year": "2004", "title": "million dollar baby", "ranking": 203, "ranking_women": 163, "ranking_men": 162, "gender_score": 0.002004008016032066}, {"year": "2005", "title": "babam ve oglum", "ranking": 117, "ranking_women": 526, "ranking_men": 291, "gender_score": 0.4709418837675351}, {"year": "1963", "title": "the great escape", "ranking": 126, "ranking_women": 479, "ranking_men": 174, "gender_score": 0.6112224448897795}, {"year": "1948", "title": "bicycle thieves", "ranking": 96, "ranking_women": 458, "ranking_men": 202, "gender_score": 0.5130260521042084}, {"year": "2004", "title": "harry potter and the prisoner of azkaban >", "ranking": 250, "ranking_women": 72, "ranking_men": 339, "gender_score": -0.5350701402805611}, {"year": "2006", "title": "blood diamond >", "ranking": 250, "ranking_women": 172, "ranking_men": 212, "gender_score": -0.08016032064128253}, {"year": "1993", "title": "the nightmare before christmas >", "ranking": 250, "ranking_women": 105, "ranking_men": 318, "gender_score": -0.42685370741482964}, {"year": "1974", "title": "chinatown", "ranking": 129, "ranking_women": 360, "ranking_men": 158, "gender_score": 0.404809619238477}, {"year": "2012", "title": "the perks of being a wallflower >", "ranking": 250, "ranking_women": 108, "ranking_men": 232, "gender_score": -0.24849699398797598}, {"year": "1990", "title": "edward scissorhands >", "ranking": 250, "ranking_women": 67, "ranking_men": 357, "gender_score": -0.5811623246492986}, {"year": "1949", "title": "the third man", "ranking": 127, "ranking_women": 484, "ranking_men": 224, "gender_score": 0.5210420841683366}, {"year": "2003", "title": "big fish >", "ranking": 250, "ranking_women": 133, "ranking_men": 226, "gender_score": -0.18637274549098193}, {"year": "2013", "title": "rush", "ranking": 193, "ranking_women": 252, "ranking_men": 172, "gender_score": 0.16032064128256507}, {"year": "1954", "title": "dial m for murder", "ranking": 155, "ranking_women": 352, "ranking_men": 233, "gender_score": 0.23847695390781565}, {"year": "1995", "title": "before sunrise", "ranking": 211, "ranking_women": 179, "ranking_men": 228, "gender_score": -0.09819639278557113}, {"year": "1940", "title": "rebecca", "ranking": 173, "ranking_women": 250, "ranking_men": 350, "gender_score": -0.2004008016032065}, {"year": "1992", "title": "unforgiven", "ranking": 120, "ranking_women": 543, "ranking_men": 110, "gender_score": 0.8677354709418837}, {"year": "1979", "title": "life of brian", "ranking": 183, "ranking_women": 266, "ranking_men": 179, "gender_score": 0.17434869739478953}, {"year": "1998", "title": "the big lebowski", "ranking": 167, "ranking_women": 256, "ranking_men": 123, "gender_score": 0.26653306613226446}, {"year": "1992", "title": "aladdin >", "ranking": 250, "ranking_women": 120, "ranking_men": 308, "gender_score": -0.376753507014028}, {"year": "2000", "title": "amores perros", "ranking": 209, "ranking_women": 260, "ranking_men": 225, "gender_score": 0.0701402805611222}, {"year": "2007", "title": "the bourne ultimatum", "ranking": 234, "ranking_women": 235, "ranking_men": 156, "gender_score": 0.1583166332665331}, {"year": "2007", "title": "ratatouille >", "ranking": 250, "ranking_women": 138, "ranking_men": 211, "gender_score": -0.14629258517034072}, {"year": "1996", "title": "fargo", "ranking": 161, "ranking_women": 230, "ranking_men": 164, "gender_score": 0.13226452905811625}, {"year": "1995", "title": "twelve monkeys", "ranking": 245, "ranking_women": 238, "ranking_men": 163, "gender_score": 0.15030060120240474}, {"year": "1965", "title": "for a few dollars more", "ranking": 104, "ranking_women": 792, "ranking_men": 142, "gender_score": 1.3026052104208417}, {"year": "1980", "title": "raging bull", "ranking": 124, "ranking_women": 599, "ranking_men": 119, "gender_score": 0.9619238476953909}, {"year": "2005", "title": "serenity >", "ranking": 250, "ranking_women": 208, "ranking_men": 295, "gender_score": -0.17434869739478953}, {"year": "1967", "title": "cool hand luke", "ranking": 172, "ranking_women": 539, "ranking_men": 215, "gender_score": 0.6492985971943888}, {"year": "1969", "title": "butch cassidy and the sundance kid", "ranking": 210, "ranking_women": 421, "ranking_men": 231, "gender_score": 0.3807615230460921}, {"year": "1957", "title": "the bridge on the river kwai", "ranking": 138, "ranking_women": 581, "ranking_men": 180, "gender_score": 0.8036072144288577}, {"year": "1988", "title": "rain man >", "ranking": 250, "ranking_women": 182, "ranking_men": 217, "gender_score": -0.0701402805611222}, {"year": "1965", "title": "the sound of music >", "ranking": 250, "ranking_women": 101, "ranking_men": 516, "gender_score": -0.8316633266533067}, {"year": "1957", "title": "the seventh seal", "ranking": 141, "ranking_women": 462, "ranking_men": 223, "gender_score": 0.47895791583166336}, {"year": "1993", "title": "in the name of the father", "ranking": 188, "ranking_women": 408, "ranking_men": 268, "gender_score": 0.28056112224448904}, {"year": "2014", "title": "wild tales", "ranking": 185, "ranking_women": 323, "ranking_men": 282, "gender_score": 0.0821643286573146}, {"year": "1939", "title": "mr. smith goes to washington", "ranking": 145, "ranking_women": 466, "ranking_men": 297, "gender_score": 0.33867735470941884}, {"year": "2006", "title": "the pursuit of happyness >", "ranking": 250, "ranking_women": 185, "ranking_men": 220, "gender_score": -0.07014028056112231}, {"year": "1995", "title": "casino", "ranking": 146, "ranking_women": 419, "ranking_men": 136, "gender_score": 0.5671342685370742}, {"year": "1987", "title": "the princess bride", "ranking": 214, "ranking_women": 136, "ranking_men": 298, "gender_score": -0.3246492985971945}, {"year": "1950", "title": "rashomon", "ranking": 110, "ranking_women": 626, "ranking_men": 185, "gender_score": 0.8837675350701404}, {"year": "2008", "title": "iron man >", "ranking": 250, "ranking_women": 140, "ranking_men": 244, "gender_score": -0.20841683366733466}, {"year": "1975", "title": "dog day afternoon >", "ranking": 250, "ranking_women": 417, "ranking_men": 252, "gender_score": 0.3306613226452906}, {"year": "2014", "title": "pk >", "ranking": 250, "ranking_women": 646, "ranking_men": 246, "gender_score": 0.8016032064128258}, {"year": "2005", "title": "sin city >", "ranking": 250, "ranking_women": 231, "ranking_men": 148, "gender_score": 0.16633266533066138}, {"year": "1954", "title": "on the waterfront", "ranking": 139, "ranking_women": 546, "ranking_men": 237, "gender_score": 0.6192384769539079}, {"year": "1982", "title": "gandhi", "ranking": 227, "ranking_women": 370, "ranking_men": 221, "gender_score": 0.2985971943887775}, {"year": "2017", "title": "call me by your name", "ranking": 186, "ranking_women": 347, "ranking_men": 528, "gender_score": -0.36272545090180364}, {"year": "2011", "title": "x: first class >", "ranking": 250, "ranking_women": 157, "ranking_men": 248, "gender_score": -0.1823647294589178}, {"year": "1948", "title": "the treasure of the sierra madre", "ranking": 119, "ranking_women": 786, "ranking_men": 230, "gender_score": 1.1142284569138274}, {"year": "2014", "title": "kingsman: the secret service >", "ranking": 250, "ranking_women": 174, "ranking_men": 259, "gender_score": -0.1703406813627254}, {"year": "2012", "title": "life of pi >", "ranking": 250, "ranking_women": 152, "ranking_men": 257, "gender_score": -0.21042084168336672}, {"year": "2016", "title": "captain america: civil war >", "ranking": 250, "ranking_women": 215, "ranking_men": 265, "gender_score": -0.1002004008016032}, {"year": "2005", "title": "harry potter and the goblet of fire >", "ranking": 250, "ranking_women": 96, "ranking_men": 431, "gender_score": -0.6713426853707415}, {"year": "2004", "title": "the notebook >", "ranking": 250, "ranking_women": 63, "ranking_men": 452, "gender_score": -0.779559118236473}, {"year": "1976", "title": "rocky", "ranking": 220, "ranking_women": 442, "ranking_men": 132, "gender_score": 0.62124248496994}, {"year": "2013", "title": "about time >", "ranking": 250, "ranking_women": 189, "ranking_men": 269, "gender_score": -0.16032064128256518}, {"year": "1977", "title": "annie hall", "ranking": 233, "ranking_women": 289, "ranking_men": 218, "gender_score": 0.14228456913827658}, {"year": "2003", "title": "mystic river >", "ranking": 250, "ranking_women": 245, "ranking_men": 219, "gender_score": 0.05210420841683372}, {"year": "2011", "title": "the girl with the dragon tattoo >", "ranking": 250, "ranking_women": 216, "ranking_men": 222, "gender_score": -0.012024048096192397}, {"year": "1992", "title": "scent of a woman >", "ranking": 250, "ranking_women": 276, "ranking_men": 255, "gender_score": 0.04208416833667339}, {"year": "2007", "title": "atonement >", "ranking": 250, "ranking_women": 139, "ranking_men": 366, "gender_score": -0.45490981963927846}, {"year": "2011", "title": "the artist >", "ranking": 250, "ranking_women": 197, "ranking_men": 325, "gender_score": -0.25651302605210424}, {"year": "2014", "title": "big hero 6 >", "ranking": 250, "ranking_women": 129, "ranking_men": 462, "gender_score": -0.6673346693386774}, {"year": "1986", "title": "platoon", "ranking": 187, "ranking_women": 490, "ranking_men": 176, "gender_score": 0.6292585170340681}, {"year": "1984", "title": "nausicaa of the valley of the wind", "ranking": 213, "ranking_women": 378, "ranking_men": 301, "gender_score": 0.15430861723446887}, {"year": "1973", "title": "the exorcist >", "ranking": 250, "ranking_women": 309, "ranking_men": 178, "gender_score": 0.26252505010020033}, {"year": "1925", "title": "the gold rush", "ranking": 136, "ranking_women": 684, "ranking_men": 306, "gender_score": 0.7575150300601202}, {"year": "1953", "title": "roman holiday >", "ranking": 250, "ranking_women": 206, "ranking_men": 426, "gender_score": -0.440881763527054}, {"year": "1982", "title": "the thing", "ranking": 163, "ranking_women": 528, "ranking_men": 146, "gender_score": 0.7655310621242486}, {"year": "1984", "title": "the terminator", "ranking": 229, "ranking_women": 318, "ranking_men": 150, "gender_score": 0.3366733466933868}, {"year": "1985", "title": "the breakfast club >", "ranking": 250, "ranking_women": 137, "ranking_men": 391, "gender_score": -0.5090180360721442}, {"year": "2007", "title": "persepolis >", "ranking": 250, "ranking_women": 291, "ranking_men": 477, "gender_score": -0.37274549098196386}, {"year": "2004", "title": "before sunset >", "ranking": 250, "ranking_women": 263, "ranking_men": 240, "gender_score": 0.04609218436873752}, {"year": "1959", "title": "ben-hur", "ranking": 195, "ranking_women": 481, "ranking_men": 227, "gender_score": 0.5090180360721442}, {"year": "1961", "title": "judgment at nuremberg", "ranking": 134, "ranking_women": 752, "ranking_men": 375, "gender_score": 0.7555110220440883}, {"year": "2013", "title": "the hunger games: catching fire >", "ranking": 250, "ranking_women": 83, "ranking_men": 525, "gender_score": -0.8857715430861723}, {"year": "2004", "title": "the incredibles >", "ranking": 250, "ranking_women": 222, "ranking_men": 208, "gender_score": 0.028056112224448815}, {"year": "2000", "title": "remember the titans >", "ranking": 250, "ranking_women": 312, "ranking_men": 346, "gender_score": -0.06813627254509025}, {"year": "2001", "title": "shrek >", "ranking": 250, "ranking_women": 143, "ranking_men": 323, "gender_score": -0.36072144288577146}, {"year": "1934", "title": "it happened one night", "ranking": 184, "ranking_women": 366, "ranking_men": 424, "gender_score": -0.11623246492985972}, {"year": "2001", "title": "harry potter and the sorcerer\u2019s stone >", "ranking": 250, "ranking_women": 88, "ranking_men": 530, "gender_score": -0.8857715430861723}, {"year": "2006", "title": "casino royale >", "ranking": 250, "ranking_women": 282, "ranking_men": 200, "gender_score": 0.1643286573146292}, {"year": "2014", "title": "edge of tomorrow >", "ranking": 250, "ranking_women": 293, "ranking_men": 203, "gender_score": 0.18036072144288584}, {"year": "2014", "title": "how to train your dragon 2 >", "ranking": 250, "ranking_women": 186, "ranking_men": 395, "gender_score": -0.4188376753507014}, {"year": "1941", "title": "the maltese falcon", "ranking": 216, "ranking_women": 541, "ranking_men": 271, "gender_score": 0.5410821643286573}, {"year": "2014", "title": "birdman or (the unexpected virtue of ignorance) >", "ranking": 250, "ranking_women": 299, "ranking_men": 168, "gender_score": 0.26252505010020044}, {"year": "1974", "title": "young frankenstein >", "ranking": 250, "ranking_women": 443, "ranking_men": 334, "gender_score": 0.218436873747495}, {"year": "1957", "title": "wild strawberries", "ranking": 152, "ranking_women": 609, "ranking_men": 329, "gender_score": 0.5611222444889781}, {"year": "2001", "title": "ocean\u2019s eleven >", "ranking": 250, "ranking_women": 221, "ranking_men": 262, "gender_score": -0.0821643286573146}, {"year": "2004", "title": "shaun of the dead >", "ranking": 250, "ranking_women": 233, "ranking_men": 261, "gender_score": -0.05611222444889774}, {"year": "1967", "title": "the graduate >", "ranking": 250, "ranking_women": 285, "ranking_men": 254, "gender_score": 0.06212424849699405}, {"year": "2006", "title": "the fall >", "ranking": 250, "ranking_women": 223, "ranking_men": 594, "gender_score": -0.7434869739478958}, {"year": "1995", "title": "la haine", "ranking": 231, "ranking_women": 561, "ranking_men": 276, "gender_score": 0.5711422845691383}, {"year": "2006", "title": "little miss sunshine >", "ranking": 250, "ranking_women": 149, "ranking_men": 349, "gender_score": -0.4008016032064128}, {"year": "2003", "title": "dogville >", "ranking": 250, "ranking_women": 328, "ranking_men": 365, "gender_score": -0.07414829659318634}, {"year": "2015", "title": "the hateful eight >", "ranking": 250, "ranking_women": 411, "ranking_men": 171, "gender_score": 0.4809619238476954}, {"year": "2005", "title": "pride & prejudice >", "ranking": 250, "ranking_women": 68, "ranking_men": 754, "gender_score": -1.374749498997996}, {"year": "2014", "title": "nightcrawler >", "ranking": 250, "ranking_women": 380, "ranking_men": 173, "gender_score": 0.41482965931863724}, {"year": "1990", "title": "dances with wolves >", "ranking": 250, "ranking_women": 375, "ranking_men": 264, "gender_score": 0.22244488977955912}, {"year": "1986", "title": "castle in the sky", "ranking": 250, "ranking_women": 379, "ranking_men": 310, "gender_score": 0.13827655310621245}, {"year": "2010", "title": "tangled >", "ranking": 250, "ranking_women": 93, "ranking_men": 599, "gender_score": -1.0140280561122246}, {"year": "1999", "title": "the iron giant >", "ranking": 250, "ranking_women": 418, "ranking_men": 312, "gender_score": 0.2124248496993988}, {"year": "2000", "title": "in the mood for love", "ranking": 240, "ranking_women": 358, "ranking_men": 423, "gender_score": -0.13026052104208408}, {"year": "2016", "title": "hidden figures >", "ranking": 250, "ranking_women": 180, "ranking_men": 651, "gender_score": -0.9438877755511021}, {"year": "2008", "title": "yip man >", "ranking": 250, "ranking_women": 744, "ranking_men": 214, "gender_score": 1.062124248496994}, {"year": "1951", "title": "strangers on a train >", "ranking": 250, "ranking_women": 478, "ranking_men": 371, "gender_score": 0.21442885771543085}, {"year": "1948", "title": "rope >", "ranking": 250, "ranking_women": 503, "ranking_men": 369, "gender_score": 0.26853707414829653}, {"year": "2009", "title": "moon >", "ranking": 250, "ranking_women": 350, "ranking_men": 284, "gender_score": 0.13226452905811625}, {"year": "2016", "title": "manchester by the sea >", "ranking": 250, "ranking_women": 427, "ranking_men": 243, "gender_score": 0.3687374749498997}, {"year": "1951", "title": "a streetcar named desire >", "ranking": 250, "ranking_women": 348, "ranking_men": 448, "gender_score": -0.2004008016032064}, {"year": "1986", "title": "ferris bueller\u2019s day off >", "ranking": 250, "ranking_women": 255, "ranking_men": 303, "gender_score": -0.09619238476953917}, {"year": "2001", "title": "mulholland drive >", "ranking": 250, "ranking_women": 349, "ranking_men": 242, "gender_score": 0.21442885771543096}, {"year": "2014", "title": "captain america: the winter soldier >", "ranking": 250, "ranking_women": 204, "ranking_men": 316, "gender_score": -0.22444889779559107}, {"year": "2009", "title": "district 9 >", "ranking": 250, "ranking_women": 324, "ranking_men": 193, "gender_score": 0.26252505010020044}, {"year": "1982", "title": "blade runner", "ranking": 149, "ranking_women": 341, "ranking_men": 197, "gender_score": 0.2885771543086173}, {"year": "1999", "title": "magnolia >", "ranking": 250, "ranking_women": 444, "ranking_men": 194, "gender_score": 0.501002004008016}, {"year": "1985", "title": "brazil >", "ranking": 250, "ranking_women": 554, "ranking_men": 287, "gender_score": 0.5350701402805612}, {"year": "2002", "title": "the bourne identity >", "ranking": 250, "ranking_women": 298, "ranking_men": 256, "gender_score": 0.08416833667334678}, {"year": "2002", "title": "hero >", "ranking": 250, "ranking_women": 492, "ranking_men": 355, "gender_score": 0.2745490981963927}, {"year": "2005", "title": "cinderella man >", "ranking": 250, "ranking_women": 495, "ranking_men": 286, "gender_score": 0.4188376753507014}, {"year": "2000", "title": "crouching tiger, hidden dragon >", "ranking": 250, "ranking_women": 354, "ranking_men": 313, "gender_score": 0.08216432865731471}, {"year": "1999", "title": "toy story 2 >", "ranking": 250, "ranking_women": 249, "ranking_men": 266, "gender_score": -0.03406813627254501}, {"year": "2013", "title": "star trek: into darkness >", "ranking": 250, "ranking_women": 191, "ranking_men": 417, "gender_score": -0.4529058116232465}, {"year": "1968", "title": "rosemary\u2019s baby >", "ranking": 250, "ranking_women": 343, "ranking_men": 304, "gender_score": 0.07815631262525047}, {"year": "1946", "title": "notorious >", "ranking": 250, "ranking_women": 500, "ranking_men": 450, "gender_score": 0.1002004008016032}, {"year": "1976", "title": "network", "ranking": 191, "ranking_women": 720, "ranking_men": 273, "gender_score": 0.8957915831663327}, {"year": "2016", "title": "rogue one >", "ranking": 250, "ranking_women": 283, "ranking_men": 337, "gender_score": -0.10821643286573146}, {"year": "1997", "title": "children of heaven", "ranking": 128, "ranking_women": 678, "ranking_men": 519, "gender_score": 0.3186372745490982}, {"year": "2007", "title": "hot fuzz >", "ranking": 250, "ranking_women": 259, "ranking_men": 331, "gender_score": -0.14428857715430865}, {"year": "1983", "title": "a christmas story >", "ranking": 250, "ranking_women": 415, "ranking_men": 377, "gender_score": 0.07615230460921851}, {"year": "2004", "title": "crash >", "ranking": 250, "ranking_women": 226, "ranking_men": 336, "gender_score": -0.22044088176352705}, {"year": "2010", "title": "harry potter and the deathly hallows: part 1 >", "ranking": 250, "ranking_women": 104, "ranking_men": 696, "gender_score": -1.1863727454909818}, {"year": "1995", "title": "dilwale dulhania le jayenge >", "ranking": 250, "ranking_women": 902, "ranking_men": 437, "gender_score": 0.9318637274549098}, {"year": "2013", "title": "captain phillips >", "ranking": 250, "ranking_women": 270, "ranking_men": 340, "gender_score": -0.14028056112224452}, {"year": "2005", "title": "walk the line >", "ranking": 250, "ranking_women": 224, "ranking_men": 418, "gender_score": -0.3887775551102204}, {"year": "2017", "title": "guardians of the galaxy vol. 2 >", "ranking": 250, "ranking_women": 241, "ranking_men": 446, "gender_score": -0.4108216432865731}, {"year": "2007", "title": "elite squad >", "ranking": 250, "ranking_women": 974, "ranking_men": 307, "gender_score": 1.3366733466933869}, {"year": "1982", "title": "e.t. the extra-terrestrial >", "ranking": 250, "ranking_women": 246, "ranking_men": 370, "gender_score": -0.24849699398797598}, {"year": "2000", "title": "dancer in the dark >", "ranking": 250, "ranking_women": 400, "ranking_men": 447, "gender_score": -0.094188376753507}, {"year": "1966", "title": "persona", "ranking": 196, "ranking_women": 548, "ranking_men": 400, "gender_score": 0.29659318637274557}, {"year": "2009", "title": "the girl with the dragon tattoo >", "ranking": 250, "ranking_women": 269, "ranking_men": 412, "gender_score": -0.28657314629258523}, {"year": "2008", "title": "let the right one in >", "ranking": 250, "ranking_women": 384, "ranking_men": 270, "gender_score": 0.22845691382765532}, {"year": "2014", "title": "boyhood >", "ranking": 250, "ranking_women": 335, "ranking_men": 238, "gender_score": 0.1943887775551103}, {"year": "2012", "title": "barfi! >", "ranking": 250, "ranking_women": 877, "ranking_men": 440, "gender_score": 0.875751503006012}, {"year": "2009", "title": "mr. nobody >", "ranking": 250, "ranking_women": 253, "ranking_men": 434, "gender_score": -0.36272545090180364}, {"year": "1993", "title": "true romance >", "ranking": 250, "ranking_women": 557, "ranking_men": 280, "gender_score": 0.5551102204408818}, {"year": "2010", "title": "my name is khan >", "ranking": 250, "ranking_women": 535, "ranking_men": 517, "gender_score": 0.03607214428857719}, {"year": "2009", "title": "the hangover >", "ranking": 250, "ranking_women": 258, "ranking_men": 247, "gender_score": 0.022044088176352616}, {"year": "1926", "title": "the general", "ranking": 153, "ranking_women": 891, "ranking_men": 381, "gender_score": 1.0220440881763526}, {"year": "2012", "title": "moonrise kingdom >", "ranking": 250, "ranking_women": 232, "ranking_men": 386, "gender_score": -0.30861723446893785}, {"year": "2012", "title": "les miserables >", "ranking": 250, "ranking_women": 168, "ranking_men": 499, "gender_score": -0.6633266533066132}, {"year": "1979", "title": "stalker", "ranking": 197, "ranking_women": 767, "ranking_men": 347, "gender_score": 0.8416833667334669}, {"year": "2017", "title": "baby driver >", "ranking": 250, "ranking_women": 389, "ranking_men": 305, "gender_score": 0.16833667334669333}, {"year": "2012", "title": "silver linings playbook >", "ranking": 250, "ranking_women": 237, "ranking_men": 251, "gender_score": -0.028056112224448815}, {"year": "2016", "title": "contratiempo >", "ranking": 250, "ranking_women": 589, "ranking_men": 561, "gender_score": 0.05611222444889785}, {"year": "2004", "title": "the sea inside >", "ranking": 250, "ranking_women": 428, "ranking_men": 507, "gender_score": -0.158316633266533}, {"year": "2006", "title": "apocalypto >", "ranking": 250, "ranking_women": 364, "ranking_men": 373, "gender_score": -0.018036072144288595}, {"year": "1959", "title": "the 400 blows", "ranking": 200, "ranking_women": 637, "ranking_men": 374, "gender_score": 0.5270541082164328}, {"year": "2017", "title": "get out >", "ranking": 250, "ranking_women": 344, "ranking_men": 314, "gender_score": 0.060120240480961984}, {"year": "1988", "title": "akira >", "ranking": 250, "ranking_women": 882, "ranking_men": 267, "gender_score": 1.2324649298597197}, {"year": "1964", "title": "fistful of dollars >", "ranking": 250, "ranking_women": 950, "ranking_men": 278, "gender_score": 1.346693386773547}, {"year": "2009", "title": "the blind side >", "ranking": 250, "ranking_women": 198, "ranking_men": 488, "gender_score": -0.5811623246492985}, {"year": "2008", "title": "taken >", "ranking": 250, "ranking_women": 257, "ranking_men": 315, "gender_score": -0.11623246492985972}, {"year": "2008", "title": "the curious case of benjamin button >", "ranking": 250, "ranking_women": 211, "ranking_men": 320, "gender_score": -0.218436873747495}, {"year": "2007", "title": "the diving bell and the butterfly >", "ranking": 250, "ranking_women": 432, "ranking_men": 397, "gender_score": 0.0701402805611222}, {"year": "2011", "title": "drive >", "ranking": 250, "ranking_women": 361, "ranking_men": 207, "gender_score": 0.30861723446893796}, {"year": "2003", "title": "spring, summer, fall, winter\u2026 and spring >", "ranking": 250, "ranking_women": 572, "ranking_men": 416, "gender_score": 0.3126252505010019}, {"year": "1987", "title": "the untouchables >", "ranking": 250, "ranking_women": 604, "ranking_men": 300, "gender_score": 0.6092184368737474}, {"year": "1944", "title": "arsenic and old lace >", "ranking": 250, "ranking_women": 464, "ranking_men": 617, "gender_score": -0.3066132264529057}, {"year": "1996", "title": "sling blade >", "ranking": 250, "ranking_women": 715, "ranking_men": 464, "gender_score": 0.5030060120240482}, {"year": "2008", "title": "the boy in the striped pajamas >", "ranking": 250, "ranking_women": 207, "ranking_men": 601, "gender_score": -0.7895791583166334}, {"year": "2002", "title": "talk to her >", "ranking": 250, "ranking_women": 394, "ranking_men": 430, "gender_score": -0.07214428857715427}, {"year": "1979", "title": "manhattan >", "ranking": 250, "ranking_women": 508, "ranking_men": 359, "gender_score": 0.2985971943887775}, {"year": "2013", "title": "short term 12 >", "ranking": 250, "ranking_women": 474, "ranking_men": 529, "gender_score": -0.11022044088176353}, {"year": "2015", "title": "straight outta compton >", "ranking": 250, "ranking_women": 513, "ranking_men": 459, "gender_score": 0.10821643286573135}, {"year": "2010", "title": "despicable me >", "ranking": 250, "ranking_women": 145, "ranking_men": 543, "gender_score": -0.7975951903807614}, {"year": "2000", "title": "almost famous >", "ranking": 250, "ranking_women": 320, "ranking_men": 322, "gender_score": -0.004008016032064132}, {"year": "1982", "title": "pink floyd: the wall >", "ranking": 250, "ranking_women": 656, "ranking_men": 510, "gender_score": 0.29258517034068143}, {"year": "2006", "title": "children of men >", "ranking": 250, "ranking_women": 355, "ranking_men": 263, "gender_score": 0.18436873747494997}, {"year": "2014", "title": "ex machina >", "ranking": 250, "ranking_women": 362, "ranking_men": 272, "gender_score": 0.18036072144288573}, {"year": "1997", "title": "boogie nights >", "ranking": 250, "ranking_women": 660, "ranking_men": 213, "gender_score": 0.8957915831663328}, {"year": "2013", "title": "queen >", "ranking": 250, "ranking_women": 1005, "ranking_men": 484, "gender_score": 1.0440881763527052}, {"year": "1973", "title": "papillon >", "ranking": 250, "ranking_women": 831, "ranking_men": 354, "gender_score": 0.9559118236472947}, {"year": "2010", "title": "elite squad: the enemy within >", "ranking": 250, "ranking_women": 1116, "ranking_men": 352, "gender_score": 1.5310621242484967}, {"year": "2014", "title": "the theory of everything >", "ranking": 250, "ranking_women": 173, "ranking_men": 591, "gender_score": -0.8376753507014029}, {"year": "1940", "title": "the philadelphia story >", "ranking": 250, "ranking_women": 393, "ranking_men": 766, "gender_score": -0.74749498997996}, {"year": "1940", "title": "the grapes of wrath", "ranking": 221, "ranking_women": 728, "ranking_men": 403, "gender_score": 0.6513026052104208}, {"year": "1971", "title": "harold and maude >", "ranking": 250, "ranking_women": 436, "ranking_men": 685, "gender_score": -0.498997995991984}, {"year": "2016", "title": "captain fantastic >", "ranking": 250, "ranking_women": 363, "ranking_men": 505, "gender_score": -0.28456913827655306}, {"year": "1993", "title": "what\u2019s eating gilbert grape >", "ranking": 250, "ranking_women": 202, "ranking_men": 574, "gender_score": -0.7454909819639277}, {"year": "2003", "title": "memories of murder", "ranking": 199, "ranking_women": 916, "ranking_men": 330, "gender_score": 1.1743486973947896}, {"year": "2009", "title": "avatar >", "ranking": 250, "ranking_women": 228, "ranking_men": 296, "gender_score": -0.13627254509018039}, {"year": "2002", "title": "infernal affairs", "ranking": 243, "ranking_women": 875, "ranking_men": 292, "gender_score": 1.1683366733466933}, {"year": "1994", "title": "three colors: red >", "ranking": 250, "ranking_women": 644, "ranking_men": 415, "gender_score": 0.4589178356713427}, {"year": "1976", "title": "all the president\u2019s men >", "ranking": 250, "ranking_women": 755, "ranking_men": 420, "gender_score": 0.6713426853707415}, {"year": "2016", "title": "the handmaiden", "ranking": 246, "ranking_women": 595, "ranking_men": 549, "gender_score": 0.09218436873747504}, {"year": "1955", "title": "the night of the hunter >", "ranking": 250, "ranking_women": 737, "ranking_men": 471, "gender_score": 0.5330661322645289}, {"year": "1995", "title": "underground >", "ranking": 250, "ranking_women": 751, "ranking_men": 541, "gender_score": 0.42084168336673344}, {"year": "1990", "title": "the godfather: part iii >", "ranking": 250, "ranking_women": 440, "ranking_men": 358, "gender_score": 0.1643286573146292}, {"year": "1984", "title": "paris, texas", "ranking": 244, "ranking_women": 736, "ranking_men": 455, "gender_score": 0.56312625250501}, {"year": "2010", "title": "the fighter >", "ranking": 250, "ranking_women": 452, "ranking_men": 283, "gender_score": 0.33867735470941884}, {"year": "1966", "title": "who\u2019s afraid of virginia woolf? >", "ranking": 250, "ranking_women": 537, "ranking_men": 565, "gender_score": -0.05611222444889785}, {"year": "2014", "title": "the fault in our stars >", "ranking": 250, "ranking_women": 187, "ranking_men": 513, "gender_score": -0.6533066132264529}, {"year": "2005", "title": "brokeback mountain >", "ranking": 250, "ranking_women": 162, "ranking_men": 611, "gender_score": -0.8997995991983967}, {"year": "2007", "title": "chak de! india >", "ranking": 250, "ranking_women": 1278, "ranking_men": 317, "gender_score": 1.9258517034068137}, {"year": "2006", "title": "lucky number slevin >", "ranking": 250, "ranking_women": 416, "ranking_men": 363, "gender_score": 0.1062124248496995}, {"year": "1991", "title": "jfk >", "ranking": 250, "ranking_women": 847, "ranking_men": 324, "gender_score": 1.0480961923847696}, {"year": "1998", "title": "the legend of 1900", "ranking": 242, "ranking_women": 608, "ranking_men": 607, "gender_score": 0.002004008016031955}, {"year": "2017", "title": "the greatest showman >", "ranking": 250, "ranking_women": 272, "ranking_men": 972, "gender_score": -1.402805611222445}, {"year": "2000", "title": "o brother, where art thou? >", "ranking": 250, "ranking_women": 401, "ranking_men": 387, "gender_score": 0.028056112224448926}, {"year": "2010", "title": "the social network >", "ranking": 250, "ranking_women": 414, "ranking_men": 201, "gender_score": 0.42685370741482975}, {"year": "1997", "title": "gattaca >", "ranking": 250, "ranking_women": 356, "ranking_men": 390, "gender_score": -0.06813627254509014}, {"year": "2012", "title": "argo >", "ranking": 250, "ranking_women": 243, "ranking_men": 409, "gender_score": -0.33266533066132264}, {"year": "1993", "title": "groundhog day", "ranking": 230, "ranking_women": 457, "ranking_men": 210, "gender_score": 0.4949899799599199}, {"year": "1962", "title": "the manchurian candidate >", "ranking": 250, "ranking_women": 849, "ranking_men": 506, "gender_score": 0.6873747494989979}, {"year": "1984", "title": "this is spinal tap >", "ranking": 250, "ranking_women": 762, "ranking_men": 348, "gender_score": 0.8296593186372746}, {"year": "2013", "title": "frozen >", "ranking": 250, "ranking_women": 130, "ranking_men": 692, "gender_score": -1.12625250501002}, {"year": "1990", "title": "misery >", "ranking": 250, "ranking_women": 402, "ranking_men": 466, "gender_score": -0.12825651302605212}, {"year": "2007", "title": "the man from earth >", "ranking": 250, "ranking_women": 764, "ranking_men": 290, "gender_score": 0.9498997995991985}, {"year": "1968", "title": "planet of the apes >", "ranking": 250, "ranking_women": 789, "ranking_men": 294, "gender_score": 0.9919839679358717}, {"year": "2000", "title": "cast away >", "ranking": 250, "ranking_women": 314, "ranking_men": 328, "gender_score": -0.028056112224448926}, {"year": "1998", "title": "black cat, white cat >", "ranking": 250, "ranking_women": 676, "ranking_men": 605, "gender_score": 0.14228456913827636}, {"year": "1971", "title": "willy wonka & the chocolate factory >", "ranking": 250, "ranking_women": 333, "ranking_men": 496, "gender_score": -0.32665330661322645}, {"year": "1985", "title": "ran", "ranking": 133, "ranking_women": 1207, "ranking_men": 234, "gender_score": 1.9498997995991982}, {"year": "2008", "title": "changeling >", "ranking": 250, "ranking_women": 296, "ranking_men": 405, "gender_score": -0.218436873747495}, {"year": "2006", "title": "rang de basanti", "ranking": 180, "ranking_women": 1218, "ranking_men": 236, "gender_score": 1.967935871743487}, {"year": "1989", "title": "glory >", "ranking": 250, "ranking_women": 768, "ranking_men": 427, "gender_score": 0.683366733466934}, {"year": "1989", "title": "back to the future part ii >", "ranking": 250, "ranking_women": 374, "ranking_men": 338, "gender_score": 0.07214428857715427}, {"year": "2004", "title": "the bourne supremacy >", "ranking": 250, "ranking_women": 413, "ranking_men": 333, "gender_score": 0.16032064128256518}, {"year": "2006", "title": "letters from iwo jima >", "ranking": 250, "ranking_women": 791, "ranking_men": 364, "gender_score": 0.8557114228456915}, {"year": "1952", "title": "high noon >", "ranking": 250, "ranking_women": 890, "ranking_men": 407, "gender_score": 0.9679358717434868}, {"year": "1997", "title": "the fifth element >", "ranking": 250, "ranking_women": 247, "ranking_men": 546, "gender_score": -0.5991983967935872}, {"year": "2017", "title": "wonder woman >", "ranking": 250, "ranking_women": 196, "ranking_men": 706, "gender_score": -1.0220440881763526}, {"year": "1995", "title": "ghost in the shell >", "ranking": 250, "ranking_women": 917, "ranking_men": 361, "gender_score": 1.1142284569138277}, {"year": "1961", "title": "yojimbo", "ranking": 113, "ranking_women": 1281, "ranking_men": 235, "gender_score": 2.096192384769539}, {"year": "2015", "title": "bahubali: the beginning >", "ranking": 250, "ranking_women": 1491, "ranking_men": 393, "gender_score": 2.2004008016032066}, {"year": "2007", "title": "zodiac >", "ranking": 250, "ranking_women": 435, "ranking_men": 275, "gender_score": 0.32064128256513025}, {"year": "1990", "title": "awakenings >", "ranking": 250, "ranking_women": 467, "ranking_men": 559, "gender_score": -0.18436873747494986}, {"year": "1993", "title": "three colors: blue >", "ranking": 250, "ranking_women": 552, "ranking_men": 603, "gender_score": -0.10220440881763526}, {"year": "1950", "title": "harvey >", "ranking": 250, "ranking_women": 645, "ranking_men": 680, "gender_score": -0.0701402805611222}, {"year": "2014", "title": "fury >", "ranking": 250, "ranking_women": 449, "ranking_men": 341, "gender_score": 0.21643286573146292}, {"year": "1993", "title": "philadelphia >", "ranking": 250, "ranking_women": 277, "ranking_men": 644, "gender_score": -0.7354709418837676}, {"year": "1998", "title": "the celebration >", "ranking": 250, "ranking_women": 785, "ranking_men": 404, "gender_score": 0.7635270541082164}, {"year": "1946", "title": "the big sleep >", "ranking": 250, "ranking_women": 750, "ranking_men": 489, "gender_score": 0.5230460921843688}, {"year": "1987", "title": "wings of desire >", "ranking": 250, "ranking_women": 622, "ranking_men": 638, "gender_score": -0.03206412825651306}, {"year": "2016", "title": "hunt for the wilderpeople >", "ranking": 250, "ranking_women": 605, "ranking_men": 701, "gender_score": -0.19238476953907813}, {"year": "1994", "title": "chungking express >", "ranking": 250, "ranking_women": 712, "ranking_men": 600, "gender_score": 0.22444889779559118}, {"year": "2012", "title": "kahaani >", "ranking": 250, "ranking_women": 1212, "ranking_men": 478, "gender_score": 1.4709418837675352}, {"year": "1958", "title": "touch of evil", "ranking": 228, "ranking_women": 1008, "ranking_men": 356, "gender_score": 1.3066132264529058}, {"year": "2004", "title": "finding neverland >", "ranking": 250, "ranking_women": 240, "ranking_men": 570, "gender_score": -0.6613226452905812}, {"year": "2004", "title": "the machinist >", "ranking": 250, "ranking_women": 330, "ranking_men": 438, "gender_score": -0.21643286573146292}, {"year": "1987", "title": "empire of the sun >", "ranking": 250, "ranking_women": 530, "ranking_men": 668, "gender_score": -0.2765531062124247}, {"year": "2012", "title": "wreck-it ralph >", "ranking": 250, "ranking_women": 281, "ranking_men": 458, "gender_score": -0.35470941883767537}, {"year": "1968", "title": "night of the living dead >", "ranking": 250, "ranking_women": 837, "ranking_men": 385, "gender_score": 0.9058116232464929}, {"year": "1993", "title": "carlito\u2019s way >", "ranking": 250, "ranking_women": 876, "ranking_men": 326, "gender_score": 1.1022044088176353}, {"year": "1996", "title": "the bandit", "ranking": 171, "ranking_women": 1181, "ranking_men": 362, "gender_score": 1.6412825651302607}, {"year": "1997", "title": "the game >", "ranking": 250, "ranking_women": 441, "ranking_men": 367, "gender_score": 0.14829659318637278}, {"year": "1946", "title": "the best years of our lives", "ranking": 239, "ranking_women": 772, "ranking_men": 604, "gender_score": 0.3366733466933869}, {"year": "2004", "title": "man on fire >", "ranking": 250, "ranking_women": 406, "ranking_men": 444, "gender_score": -0.0761523046092184}, {"year": "2014", "title": "the lego movie >", "ranking": 250, "ranking_women": 397, "ranking_men": 380, "gender_score": 0.034068136272545124}, {"year": "1964", "title": "mary poppins >", "ranking": 250, "ranking_women": 234, "ranking_men": 806, "gender_score": -1.1462925851703405}, {"year": "1959", "title": "anatomy of a murder >", "ranking": 250, "ranking_women": 864, "ranking_men": 515, "gender_score": 0.6993987975951905}, {"year": "1999", "title": "being john malkovich >", "ranking": 250, "ranking_women": 392, "ranking_men": 383, "gender_score": 0.018036072144288595}, {"year": "2015", "title": "the big short >", "ranking": 250, "ranking_women": 515, "ranking_men": 299, "gender_score": 0.43286573146292573}, {"year": "2008", "title": "the wrestler >", "ranking": 250, "ranking_women": 621, "ranking_men": 289, "gender_score": 0.6653306613226452}, {"year": "1954", "title": "la strada >", "ranking": 250, "ranking_women": 748, "ranking_men": 623, "gender_score": 0.25050100200400816}, {"year": "1999", "title": "all about my mother >", "ranking": 250, "ranking_women": 405, "ranking_men": 712, "gender_score": -0.6152304609218436}, {"year": "2007", "title": "3:10 to yuma >", "ranking": 250, "ranking_women": 511, "ranking_men": 456, "gender_score": 0.11022044088176342}, {"year": "1975", "title": "barry lyndon", "ranking": 225, "ranking_women": 991, "ranking_men": 281, "gender_score": 1.4228456913827654}, {"year": "2009", "title": "fantastic mr. fox >", "ranking": 250, "ranking_women": 423, "ranking_men": 445, "gender_score": -0.044088176352705455}, {"year": "1922", "title": "nosferatu >", "ranking": 250, "ranking_women": 716, "ranking_men": 468, "gender_score": 0.49699398797595185}, {"year": "2017", "title": "wonder >", "ranking": 250, "ranking_women": 577, "ranking_men": 862, "gender_score": -0.5711422845691383}, {"year": "2006", "title": "the last king of scotland >", "ranking": 250, "ranking_women": 455, "ranking_men": 535, "gender_score": -0.16032064128256507}, {"year": "1980", "title": "the blues brothers >", "ranking": 250, "ranking_women": 687, "ranking_men": 372, "gender_score": 0.6312625250501003}, {"year": "2012", "title": "skyfall >", "ranking": 250, "ranking_women": 295, "ranking_men": 401, "gender_score": -0.2124248496993988}, {"year": "1997", "title": "as good as it gets >", "ranking": 250, "ranking_women": 367, "ranking_men": 396, "gender_score": -0.05811623246492992}, {"year": "1955", "title": "diabolique", "ranking": 223, "ranking_women": 910, "ranking_men": 534, "gender_score": 0.753507014028056}, {"year": "2016", "title": "kubo and the two strings >", "ranking": 250, "ranking_women": 600, "ranking_men": 616, "gender_score": -0.03206412825651306}, {"year": "1972", "title": "solaris >", "ranking": 250, "ranking_women": 996, "ranking_men": 429, "gender_score": 1.1362725450901805}, {"year": "2013", "title": "before midnight >", "ranking": 250, "ranking_women": 453, "ranking_men": 449, "gender_score": 0.008016032064128265}, {"year": "1989", "title": "kiki\u2019s delivery service >", "ranking": 250, "ranking_women": 357, "ranking_men": 674, "gender_score": -0.6352705410821642}, {"year": "1994", "title": "ed wood >", "ranking": 250, "ranking_women": 545, "ranking_men": 384, "gender_score": 0.3226452905811623}, {"year": "1960", "title": "la dolce vita >", "ranking": 250, "ranking_women": 793, "ranking_men": 512, "gender_score": 0.56312625250501}, {"year": "1993", "title": "the fugitive >", "ranking": 250, "ranking_women": 569, "ranking_men": 392, "gender_score": 0.35470941883767537}, {"year": "1967", "title": "bonnie and clyde >", "ranking": 250, "ranking_women": 648, "ranking_men": 501, "gender_score": 0.2945891783567136}, {"year": "1996", "title": "primal fear >", "ranking": 250, "ranking_women": 426, "ranking_men": 578, "gender_score": -0.3046092184368737}, {"year": "2002", "title": "harry potter and the chamber of secrets >", "ranking": 250, "ranking_women": 142, "ranking_men": 831, "gender_score": -1.3807615230460923}, {"year": "1999", "title": "the insider >", "ranking": 250, "ranking_women": 863, "ranking_men": 378, "gender_score": 0.9719438877755511}, {"year": "2004", "title": "3-iron >", "ranking": 250, "ranking_women": 651, "ranking_men": 719, "gender_score": -0.1362725450901805}, {"year": "1965", "title": "doctor zhivago >", "ranking": 250, "ranking_women": 714, "ranking_men": 577, "gender_score": 0.2745490981963927}, {"year": "1927", "title": "sunrise", "ranking": 164, "ranking_women": 995, "ranking_men": 633, "gender_score": 0.7254509018036073}, {"year": "2009", "title": "zombieland >", "ranking": 250, "ranking_women": 329, "ranking_men": 414, "gender_score": -0.1703406813627255}, {"year": "2001", "title": "lagaan: once upon a time in india", "ranking": 249, "ranking_women": 1190, "ranking_men": 293, "gender_score": 1.7975951903807612}, {"year": "1993", "title": "tombstone >", "ranking": 250, "ranking_women": 794, "ranking_men": 526, "gender_score": 0.5370741482965931}, {"year": "2008", "title": "departures >", "ranking": 250, "ranking_women": 731, "ranking_men": 613, "gender_score": 0.23647294589178358}, {"year": "2009", "title": "(500) days of summer >", "ranking": 250, "ranking_women": 310, "ranking_men": 345, "gender_score": -0.07014028056112231}, {"year": "1969", "title": "midnight cowboy >", "ranking": 250, "ranking_women": 818, "ranking_men": 502, "gender_score": 0.6332665330661322}, {"year": "1961", "title": "breakfast at tiffany\u2019s >", "ranking": 250, "ranking_women": 210, "ranking_men": 802, "gender_score": -1.1863727454909818}, {"year": "2007", "title": "harry potter and the order of the phoenix >", "ranking": 250, "ranking_women": 147, "ranking_men": 837, "gender_score": -1.382765531062124}, {"year": "2004", "title": "the butterfly effect >", "ranking": 250, "ranking_women": 303, "ranking_men": 428, "gender_score": -0.25050100200400793}, {"year": "2003", "title": "21 grams >", "ranking": 250, "ranking_women": 410, "ranking_men": 500, "gender_score": -0.18036072144288573}, {"year": "2016", "title": "doctor strange >", "ranking": 250, "ranking_women": 287, "ranking_men": 556, "gender_score": -0.5390781563126251}, {"year": "2009", "title": "harry potter and the half-blood prince >", "ranking": 250, "ranking_women": 160, "ranking_men": 846, "gender_score": -1.374749498997996}, {"year": "1953", "title": "stalag 17 >", "ranking": 250, "ranking_women": 1059, "ranking_men": 642, "gender_score": 0.8356713426853708}, {"year": "1962", "title": "what ever happened to baby jane? >", "ranking": 250, "ranking_women": 585, "ranking_men": 793, "gender_score": -0.4168336673346693}, {"year": "2007", "title": "once >", "ranking": 250, "ranking_women": 463, "ranking_men": 487, "gender_score": -0.048096192384769476}, {"year": "2013", "title": "mandariinid >", "ranking": 250, "ranking_women": 666, "ranking_men": 865, "gender_score": -0.3987975951903806}]